htamd/__init__.py
htamd-0.2.dist-info/LICENCE.txt
htamd-0.2.dist-info/METADATA
htamd-0.2.dist-info/WHEEL
htamd-0.2.dist-info/top_level.txt
htamd-0.2.dist-info/RECORD
