Metadata-Version: 2.1
Name: htamd
Version: 0.2
Summary: A Hand tracking module
Author: Advaith S
Author-email: <popular9adu@gmail.com>
Keywords: python,Hand tracking
Classifier: Development Status :: 1 - Planning
Classifier: Intended Audience :: Developers
Classifier: Programming Language :: Python :: 3
Classifier: Operating System :: Unix
Classifier: Operating System :: MacOS :: MacOS X
License-File: LICENCE.txt
Requires-Dist: opencv-python
Requires-Dist: mediapipe
